{
  "Jaune (9e keup)": [
    {
      "id": 2001,
      "question": "Quelle est la position de marche en Taekwondo ?",
      "options": ["Ap Seugui", "Joutchoum Seugui", "Tchaliot Seugui"],
      "correctAnswer": "Ap Seugui",
      "image": "assets/images/ceinture_jaune.png"
    },
    {
      "id": 2002,
      "question": "Quelle position est utilisée pour saluer en Taekwondo ?",
      "options": ["Tchaliot Seugui", "Ap Seugui", "Narahni Tchoumbi Seugui"],
      "correctAnswer": "Tchaliot Seugui",
      "image": "assets/images/ceinture_jaune.png"
    },
    {
      "id": 2003,
      "question": "Comment s'appelle la position d'attente avec les pieds parallèles ?",
      "options": ["Narahni Tchoumbi Seugui", "Ap Seugui", "Tchaliot Seugui"],
      "correctAnswer": "Narahni Tchoumbi Seugui",
      "image": "assets/images/ceinture_jaune.png"
    },
    {
      "id": 2004,
      "question": "Quelle est la position basse en Taekwondo ?",
      "options": ["Ap Koubi", "Ap Seugui", "Joutchoum Seugui"],
      "correctAnswer": "Ap Koubi",
      "image": "assets/images/ceinture_jaune.png"
    },
    {
      "id": 2005,
      "question": "Quelle est la position du cavalier ?",
      "options": ["Joutchoum Seugui", "Narahni Tchoumbi Seugui", "Ap Koubi"],
      "correctAnswer": "Joutchoum Seugui",
      "image": "assets/images/ceinture_jaune.png"
    },
    {
      "id": 2006,
      "question": "Comment s'appelle le coup de poing moyen en Taekwondo ?",
      "options": ["Momtong Jireugui", "Eulgoul Jireugui", "Baro Jireugui"],
      "correctAnswer": "Momtong Jireugui",
      "image": "assets/images/ceinture_jaune.png"
    },
    {
      "id": 2007,
      "question": "Quel est le nom du coup de poing réalisé avec le poing arrière ?",
      "options": ["Baro Jireugui", "Bandé Jireugui", "Toubon Jireugui"],
      "correctAnswer": "Baro Jireugui",
      "image": "assets/images/ceinture_jaune.png"
    },
    {
      "id": 2008,
      "question": "Quel coup de poing est utilisé pour frapper avec le poing avant ?",
      "options": ["Bandé Jireugui", "Baro Jireugui", "Toubon Jireugui"],
      "correctAnswer": "Bandé Jireugui",
      "image": "assets/images/ceinture_jaune.png"
    },
    {
      "id": 2009,
      "question": "Quel coup de poing consiste à frapper avec le poing avant et arrière alternativement ?",
      "options": ["Toubon Jireugui", "Bandé Jireugui", "Baro Jireugui"],
      "correctAnswer": "Toubon Jireugui",
      "image": "assets/images/ceinture_jaune.png"
    },
    {
      "id": 2010,
      "question": "Quel est le coup de poing haut en Taekwondo ?",
      "options": ["Eulgoul Jireugui", "Momtong Jireugui", "Bandé Jireugui"],
      "correctAnswer": "Eulgoul Jireugui",
      "image": "assets/images/ceinture_jaune.png"
    },
    {
      "id": 2011,
      "question": "Quel coup de pied est un coup de pied de face ?",
      "options": ["Ap Tchagui", "Bandal Tchagui", "Mireu Tchagui"],
      "correctAnswer": "Ap Tchagui",
      "image": "assets/images/ceinture_jaune.png"
    },
    {
      "id": 2012,
      "question": "Quel coup de pied est un coup semi-circulaire ?",
      "options": ["Bandal Tchagui", "Mireu Tchagui", "An Tchagui"],
      "correctAnswer": "Bandal Tchagui",
      "image": "assets/images/ceinture_jaune.png"
    },
    {
      "id": 2013,
      "question": "Comment s'appelle le coup de pied de base poussé de face ?",
      "options": ["Mireu Tchagui", "Bakat Tchagui", "Ap Tchagui"],
      "correctAnswer": "Mireu Tchagui",
      "image": "assets/images/ceinture_jaune.png"
    },
    {
      "id": 2014,
      "question": "Quel est le coup de pied balancé de l'extérieur vers l'intérieur ?",
      "options": ["An Tchagui", "Bakat Tchagui", "Bandal Tchagui"],
      "correctAnswer": "An Tchagui",
      "image": "assets/images/ceinture_jaune.png"
    },
    {
      "id": 2015,
      "question": "Quel coup de pied est un balancement de l'intérieur vers l'extérieur ?",
      "options": ["Bakat Tchagui", "An Tchagui", "Mireu Tchagui"],
      "correctAnswer": "Bakat Tchagui",
      "image": "assets/images/ceinture_jaune.png"
    },
    {
      "id": 2016,
      "question": "Comment s'appelle le blocage réalisé en bas ?",
      "options": ["Are Maki", "Eulgoul Maki", "Momtong Maki"],
      "correctAnswer": "Are Maki",
      "image": "assets/images/ceinture_jaune.png"
    },
    {
      "id": 2017,
      "question": "Quel blocage est réalisé en haut avec le poing fermé ?",
      "options": ["Eulgoul Maki", "Are Maki", "Momtong Maki"],
      "correctAnswer": "Eulgoul Maki",
      "image": "assets/images/ceinture_jaune.png"
    },
    {
      "id": 2018,
      "question": "Quel est le blocage moyen réalisé avec le bras avant ?",
      "options": ["Momtong Maki", "Are Maki", "Eulgoul Maki"],
      "correctAnswer": "Momtong Maki",
      "image": "assets/images/ceinture_jaune.png"
    },
    {
      "id": 2019,
      "question": "Quel blocage est réalisé avec le bras arrière en moyen ?",
      "options": ["Momtong An Maki", "Momtong Maki", "Are Maki"],
      "correctAnswer": "Momtong An Maki",
      "image": "assets/images/ceinture_jaune.png"
    }
  ]
}
